AUTHORS
CHANGELOG.md
COPYING
MANIFEST.in
README
setup.py
PyRDM.egg-info/PKG-INFO
PyRDM.egg-info/SOURCES.txt
PyRDM.egg-info/dependency_links.txt
PyRDM.egg-info/requires.txt
PyRDM.egg-info/top_level.txt
bin/fluidity-publish
bin/pyrdm-publish
pyrdm/__init__.py
pyrdm/dspace.py
pyrdm/figshare.py
pyrdm/git_handler.py
pyrdm/publisher.py
pyrdm/zenodo.py